muridesu/__init__.py
muridesu/cli.py
muridesu/helper.py
muridesu/parse_stmts.py
muridesu/parser.py
muridesu/wrap_parser.py
muridesu-0.0.58.dist-info/LICENSE
muridesu-0.0.58.dist-info/METADATA
muridesu-0.0.58.dist-info/WHEEL
muridesu-0.0.58.dist-info/entry_points.txt
muridesu-0.0.58.dist-info/top_level.txt
muridesu-0.0.58.dist-info/RECORD
