Metadata-Version: 2.1
Name: muridesu
Version: 0.0.58
Summary: UNKNOWN
Home-page: https://github.com/thautawarm/muridesu
Author: thautawarm
Author-email: twshere@outlook.com
License: mit
Platform: any
Classifier: Programming Language :: Python :: 3.7
Classifier: Programming Language :: Python :: Implementation :: CPython
Requires-Python: >=3.7, <3.8
Requires-Dist: devpackage
Requires-Dist: argser
Requires-Dist: rbnf-rts
Requires-Dist: remu-operator
